{
    "family": "langflow-task",
    "networkMode": "awsvpc",
    "executionRoleArn": "arn:aws:iam::590184002626:role/ecsTaskExecutionRole",
    "containerDefinitions": [
      {
        "name": "langflow-container",
        "image": "590184002626.dkr.ecr.us-east-2.amazonaws.com/langflow:latest",
        "cpu": 256,
        "memory": 512,
        "essential": true,
        "portMappings": [
          {
            "containerPort": 8000,
            "hostPort": 8000
          }
        ]
      }
    ],
    "requiresCompatibilities": [
      "FARGATE"
    ],
    "cpu": "256",
    "memory": "512"
  }
  